atlasopenmagic/__init__.py
atlasopenmagic/metadata.py
atlasopenmagic/utils.py
atlasopenmagic-1.7.0.dist-info/METADATA
atlasopenmagic-1.7.0.dist-info/WHEEL
atlasopenmagic-1.7.0.dist-info/licenses/LICENSE
atlasopenmagic-1.7.0.dist-info/RECORD
