Metadata-Version: 2.4
Name: atlasopenmagic
Version: 1.7.0
Summary: A utility package for retrieving ATLAS open data URLs and metadata.
Project-URL: Homepage, https://opendata.atlas.cern/
Project-URL: Repository, https://github.com/atlas-outreach-data-tools/atlasopenmagic
Project-URL: Documentation, https://opendata.atlas.cern/docs/atlasopenmagic
Author-email: ATLAS Collaboration <atlas-outreach-opendata-support@cern.ch>
License-Expression: Apache-2.0
License-File: LICENSE
Keywords: ATLAS,Open Data,Utilities
Classifier: Development Status :: 5 - Production/Stable
Classifier: Intended Audience :: Education
Classifier: Intended Audience :: Science/Research
Classifier: License :: OSI Approved
Classifier: License :: OSI Approved :: Apache Software License
Classifier: Natural Language :: English
Classifier: Operating System :: OS Independent
Classifier: Programming Language :: Python :: 3
Classifier: Programming Language :: Python :: 3.10
Classifier: Programming Language :: Python :: 3.11
Classifier: Programming Language :: Python :: 3.12
Classifier: Topic :: Documentation
Classifier: Topic :: Education
Classifier: Topic :: Scientific/Engineering
Classifier: Topic :: Scientific/Engineering :: Physics
Classifier: Topic :: Utilities
Classifier: Typing :: Typed
Requires-Python: >=3.10
Requires-Dist: pyyaml
Requires-Dist: requests
Requires-Dist: tqdm
Provides-Extra: dev
Requires-Dist: pre-commit; extra == 'dev'
Requires-Dist: pylint; extra == 'dev'
Requires-Dist: pytest; extra == 'dev'
Requires-Dist: pytest-cov; extra == 'dev'
